asgi_auth_github/__init__.py
asgi_auth_github/github_auth.py
asgi_auth_github/utils.py
asgi_auth_github/templates/base.html
asgi_auth_github-0.1.1.dist-info/LICENSE
asgi_auth_github-0.1.1.dist-info/METADATA
asgi_auth_github-0.1.1.dist-info/WHEEL
asgi_auth_github-0.1.1.dist-info/top_level.txt
asgi_auth_github-0.1.1.dist-info/RECORD
