Metadata-Version: 2.1
Name: asgi-auth-github
Version: 0.1.1
Summary: ASGI middleware that authenticates users against GitHub
Home-page: https://github.com/simonw/asgi-auth-github
Author: Simon Willison
License: Apache License, Version 2.0
Platform: UNKNOWN
Provides-Extra: test
Requires-Dist: pytest ; extra == 'test'
Requires-Dist: pytest-asyncio ; extra == 'test'
Requires-Dist: asgiref (~=3.1.2) ; extra == 'test'
